.VERSION
AUTHORS.rst
CONTRIBUTING.rst
HISTORY.rst
LICENSE
MANIFEST.in
Pipfile
Pipfile.lock
README.rst
USAGE.rst
dev-requirements.txt
requirements.txt
setup.cfg
setup.py
docs/Makefile
docs/authors.rst
docs/conf.py
docs/contributing.rst
docs/history.rst
docs/index.rst
docs/installation.rst
docs/readme.rst
docs/usage.rst
terraform_validate_patched/.VERSION
terraform_validate_patched/__init__.py
terraform_validate_patched/_version.py
terraform_validate_patched/functional_test.py
terraform_validate_patched/terraform_validate_patched.py
terraform_validate_patched/unit_test.py
terraform_validate_patched.egg-info/PKG-INFO
terraform_validate_patched.egg-info/SOURCES.txt
terraform_validate_patched.egg-info/dependency_links.txt
terraform_validate_patched.egg-info/not-zip-safe
terraform_validate_patched.egg-info/requires.txt
terraform_validate_patched.egg-info/top_level.txt